CMakeLists.txt
LICENSE
MANIFEST.in
README.md
setup.py
cmake/__init__.py
cmake/asio.cmake
cmake/cmake_extension.py
cmake/googletest.cmake
cmake/json.cmake
cmake/k2.cmake
cmake/kaldi_native_io.cmake
cmake/kaldifeat.cmake
cmake/portaudio.cmake
cmake/pybind11.cmake
cmake/torch.cmake
cmake/websocketpp.cmake
cmake/__pycache__/__init__.cpython-38.pyc
cmake/__pycache__/cmake_extension.cpython-38.pyc
k2_sherpa.egg-info/PKG-INFO
k2_sherpa.egg-info/SOURCES.txt
k2_sherpa.egg-info/dependency_links.txt
k2_sherpa.egg-info/not-zip-safe
k2_sherpa.egg-info/top_level.txt
sherpa/CMakeLists.txt
sherpa/bin/.gitignore
sherpa/bin/README.md
sherpa/bin/offline_ctc_asr.py
sherpa/bin/offline_transducer_asr.py
sherpa/bin/conv_emformer_transducer_stateless2/beam_search.py
sherpa/bin/conv_emformer_transducer_stateless2/stream.py
sherpa/bin/conv_emformer_transducer_stateless2/streaming_client.py
sherpa/bin/conv_emformer_transducer_stateless2/streaming_server.py
sherpa/bin/lstm_transducer_stateless/beam_search.py
sherpa/bin/lstm_transducer_stateless/offline_asr.py
sherpa/bin/lstm_transducer_stateless/stream.py
sherpa/bin/lstm_transducer_stateless/streaming_client.py
sherpa/bin/lstm_transducer_stateless/streaming_server.py
sherpa/bin/pruned_stateless_emformer_rnnt2/beam_search.py
sherpa/bin/pruned_stateless_emformer_rnnt2/stream.py
sherpa/bin/pruned_stateless_emformer_rnnt2/streaming_client.py
sherpa/bin/pruned_stateless_emformer_rnnt2/streaming_server.py
sherpa/bin/pruned_transducer_statelessX/__init__.py
sherpa/bin/pruned_transducer_statelessX/beam_search.py
sherpa/bin/pruned_transducer_statelessX/decode_manifest.py
sherpa/bin/pruned_transducer_statelessX/offline_asr.py
sherpa/bin/pruned_transducer_statelessX/offline_client.py
sherpa/bin/pruned_transducer_statelessX/offline_server.py
sherpa/bin/streaming_pruned_transducer_statelessX/beam_search.py
sherpa/bin/streaming_pruned_transducer_statelessX/decode_manifest.py
sherpa/bin/streaming_pruned_transducer_statelessX/stream.py
sherpa/bin/streaming_pruned_transducer_statelessX/streaming_client.py
sherpa/bin/streaming_pruned_transducer_statelessX/streaming_server.py
sherpa/bin/web/.gitignore
