Metadata-Version: 2.1
Name: k2-sherpa
Version: 1.2
Summary: UNKNOWN
Home-page: https://github.com/k2-fsa/sherpa
Author: The sherpa development team
Author-email: dpovey@gmail.com
License: Apache licensed, as found in the LICENSE file
Platform: UNKNOWN
Classifier: Programming Language :: C++
Classifier: Programming Language :: Python
Classifier: Programming Language :: Python :: 3
Classifier: Programming Language :: Python :: 3.7
Classifier: Programming Language :: Python :: 3.8
Classifier: Programming Language :: Python :: 3.9
Classifier: Topic :: Scientific/Engineering :: Artificial Intelligence
Requires-Python: >=3.7.0
